CHANGES.txt
LICENSE.txt
MANIFEST.in
README.md
README.rst
setup.py
docs/index.rst
libnessus/__init__.py
libnessus/exceptions.py
libnessus/parser.py
libnessus/objects/__init__.py
libnessus/objects/dictdiffer.py
libnessus/objects/report.py
libnessus/objects/reporthost.py
libnessus/objects/reportitem.py
libnessus/objects/reportlogger.py
libnessus/plugins/__init__.py
libnessus/plugins/backendplugin.py
libnessus/plugins/backendpluginFactory.py
libnessus/plugins/es.py
libnessus/plugins/mongodb.py
python_libnessus.egg-info/PKG-INFO
python_libnessus.egg-info/SOURCES.txt
python_libnessus.egg-info/dependency_links.txt
python_libnessus.egg-info/requires.txt
python_libnessus.egg-info/top_level.txt