Metadata-Version: 2.1
Name: python-libnessus
Version: 1.0.0.10
Summary: Python Nessus module to parse, chat with XMLRPC API, ...
Home-page: https://github.com/bmx0r/python-libnessus
Author: Ronald Bister and Mike Boutillier
Author-email: michael.boutillier@gmail.com
License: Creative Common "Attribution" license (CC-BY) v3
Download-URL: https://github.com/bmx0r/python-libnessus/tarball/1.0.0.10
Platform: UNKNOWN
Classifier: Development Status :: 4 - Beta
Classifier: Environment :: Console
Classifier: Programming Language :: Python :: 2.7
Classifier: Programming Language :: Python :: 3.4
Classifier: Programming Language :: Python :: 3.5
Classifier: Programming Language :: Python :: 3.6
Classifier: Topic :: System :: Networking
